{
    "$schema": "http://schema.management.azure.com/schemas/2015-01-01/deploymentTemplate.json#",
    "contentVersion": "1.0.0.0",
    "parameters": {
        "resourceName": {
            "type": "string"
        },
        "OSController": {
            "type": "string",
            "defaultValue": " "
        },
        "OSPrivateKey": {
            "type": "string",
            "defaultValue": " "
        },
        "OSDBServer": {
            "type": "string"
        },
        "OSDBLogServer": {
            "type": "string",
            "defaultValue": " "
        },
        "OSDBSessionServer": {
            "type": "string",
            "defaultValue": " "
        },
        "OSDBSAUser": {
            "type": "string"
        },
        "OSDBSAPass": {
            "type": "securestring"
        },
        "OSDBSALogUser": {
            "type": "string",
            "defaultValue": " "
        },
        "OSDBSALogPass": {
            "type": "securestring",
            "defaultValue": " "
        },
        "OSDBSASessionUser": {
            "type": "string",
            "defaultValue": " "
        },
        "OSDBSASessionPass": {
            "type": "securestring",
            "defaultValue": " "
        },
        "OSDBCatalog": {
            "type": "string",
            "defaultValue": " "
        },
        "OSDBLogCatalog": {
            "type": "string",
            "defaultValue": " "
        },
        "OSDBSessionCatalog": {
            "type": "string",
            "defaultValue": " "
        },
        "OSDBAdminUser": {
            "type": "string",
            "defaultValue": " "
        },
        "OSDBAdminPass": {
            "type": "securestring",
            "defaultValue": " "
        },
        "OSDBRuntimeUser": {
            "type": "string",
            "defaultValue": " "
        },
        "OSDBRuntimePass": {
            "type": "securestring",
            "defaultValue": " "
        },
        "OSDBLogUser": {
            "type": "string",
            "defaultValue": " "
        },
        "OSDBLogPass": {
            "type": "securestring",
            "defaultValue": " "
        },
        "OSDBSessionUser": {
            "type": "string",
            "defaultValue": " "
        },
        "OSDBSessionPass": {
            "type": "securestring",
            "defaultValue": " "
        },
        "OSRabbitMQHost": {
            "type": "string",
            "defaultValue": " "
        },
        "OSRabbitMQUser": {
            "type": "string",
            "defaultValue": " "
        },
        "OSRabbitMQPass": {
            "type": "securestring",
            "defaultValue": " "
        },
        "OSRabbitMQVHost": {
            "type": "string",
            "defaultValue": " "
        },
        "OSServerVersion": {
            "type": "string",
            "defaultValue": " "
        },
        "OSServiceStudioVersion": {
            "type": "string",
            "defaultValue": " "
        }
    },
    "variables": {},
    "resources": [
        {
            "name": "[concat(parameters('resourceName'), '.Outsystems.CustomScriptExtension')]",
            "apiVersion": "2015-01-01",
            "type": "Microsoft.Resources/deployments",
            "properties": {
                "mode": "Incremental",
                "templateLink": {
                    "uri": "[uri(deployment().properties.templateLink.uri, 'Resources/customScriptExtension.json')]"
                },
                "parameters": {
                    "resourceName": {
                        "value": "[parameters('resourceName')]"
                    },
                    "location": {
                        "value": "[resourceGroup().location]"
                    },
                    "fileUris": {
                        "value": "[uri(deployment().properties.templateLink.uri, 'Scripts/OutsystemsSetup.ps1')]"
                    },
                    "arguments": {
                        "value": "[[concat(' -OSController \"', trim(parameters('OSController')), '\" -OSPrivateKey \"', trim(parameters('OSPrivateKey')), '\" -OSDBServer \"', trim(parameters('OSDBServer')), '\" -OSDBLogServer \"', trim(parameters('OSDBLogServer')), '\" -OSDBSessionServer \"', trim(parameters('OSDBSessionServer')), '\" -OSDBSAUser \"', trim(parameters('OSDBSAUser')), '\" -OSDBSAPass \"', trim(parameters('OSDBSAPass')), '\" -OSDBSALogUser \"', trim(parameters('OSDBSALogUser')), '\" -OSDBSALogPass \"', trim(parameters('OSDBSALogPass')), '\" -OSDBSASessionUser \"', trim(parameters('OSDBSASessionUser')), '\" -OSDBSASessionPass \"', trim(parameters('OSDBSASessionPass')), '\" -OSDBCatalog \"', trim(parameters('OSDBCatalog')), '\" -OSDBLogCatalog \"', trim(parameters('OSDBLogCatalog')), '\" -OSDBSessionCatalog \"', trim(parameters('OSDBSessionCatalog')), '\" -OSDBAdminUser \"', trim(parameters('OSDBAdminUser')), '\" -OSDBAdminPass \"', trim(parameters('OSDBAdminPass')), '\" -OSDBRuntimeUser \"', trim(parameters('OSDBRuntimeUser')), '\" -OSDBRuntimePass \"', trim(parameters('OSDBRuntimePass')), '\" -OSDBLogUser \"', trim(parameters('OSDBLogUser')), '\" -OSDBLogPass \"', trim(parameters('OSDBLogPass')), '\" -OSDBSessionUser \"', trim(parameters('OSDBSessionUser')), '\" -OSDBSessionPass \"', trim(parameters('OSDBSessionPass')), '\" -OSRabbitMQHost \"', trim(parameters('OSRabbitMQHost')), '\" -OSRabbitMQUser \"', trim(parameters('OSRabbitMQUser')), '\" -OSRabbitMQPass \"', trim(parameters('OSRabbitMQPass')), '\" -OSRabbitMQVHost \"', trim(parameters('OSRabbitMQVHost')), '\" -OSServerVersion \"', trim(parameters('OSServerVersion')), '\" -OSServiceStudioVersion \"', trim(parameters('OSServiceStudioVersion')))]"
                    }
                }
            }
        }
    ],
    "outputs": {
        "message": {
            "type": "string",
            "value": "[reference(concat('Microsoft.Resources/deployments/', parameters('resourceName'), '.Outsystems.CustomScriptExtension')).outputs.message.value]"
        }
    }
}